jfp/__init__.py
jfp/jfp.py
JFP-0.2.dist-info/LICENSE
JFP-0.2.dist-info/METADATA
JFP-0.2.dist-info/WHEEL
JFP-0.2.dist-info/entry_points.txt
JFP-0.2.dist-info/top_level.txt
JFP-0.2.dist-info/RECORD
