Metadata-Version: 2.1
Name: JFP
Version: 0.2
Summary: A Jar file patch Tool
Home-page: https://github.com/hexpang/zfp
Author: HexPang
Author-email: hexpang@gmail.com
License: MIT Licence
Keywords: pip,zfp,zip,jar,pyZfp,zfpt,pyJFP,jfp
Platform: any
